python_tradingview_light.py
python_tradingview_light-1.0.dist-info/METADATA
python_tradingview_light-1.0.dist-info/WHEEL
python_tradingview_light-1.0.dist-info/top_level.txt
python_tradingview_light-1.0.dist-info/RECORD
