Metadata-Version: 2.1
Name: python-tradingview-light
Version: 1.0
Summary: Library Technical Analysis Tradingview
Home-page: https://github.com/GaboBegue/python_tradingview_data_wrapper
Author: Gabriel Beguerie
Author-email: gabriel.arturo.beguerie@gmail.com
License: MIT
Platform: UNKNOWN
Requires-Dist: requests
